sTTgeo.py
sttgeo-1.0.0.dist-info/WHEEL
sttgeo-1.0.0.dist-info/METADATA
sttgeo-1.0.0.dist-info/RECORD
