Metadata-Version: 2.1
Name: sttgeo
Version: 1.0.0
Summary: Information of IP.... For example: IP, TimeZone, Region, City, Country and soon...
Author: OwoNicoo
Author-email: 86409467+DiscordBotML@users.noreply.github.com
Requires-Python: >=3.9,<4.0
Classifier: Programming Language :: Python :: 3
Classifier: Programming Language :: Python :: 3.10
Classifier: Programming Language :: Python :: 3.9
